say_something/__init__.py
say_something/package.py
otus_open_lesson-0.4.0.dist-info/LICENSE
otus_open_lesson-0.4.0.dist-info/METADATA
otus_open_lesson-0.4.0.dist-info/WHEEL
otus_open_lesson-0.4.0.dist-info/top_level.txt
otus_open_lesson-0.4.0.dist-info/RECORD
